bosa_cli/__init__.py
bosa_cli/__main__.py
bosa_cli/api/__init__.py
bosa_cli/api/auth.py
bosa_cli/api/base.py
bosa_cli/api/integrations.py
bosa_cli/api/models.py
bosa_cli/api/users.py
bosa_cli/commands/__init__.py
bosa_cli/commands/auth.py
bosa_cli/commands/base.py
bosa_cli/commands/integrations.py
bosa_cli/commands/users.py
bosa_cli/config.py
bosa_cli/constants.py
bosa_cli/main.py
bosa_cli/utils.py
bosa_cli-0.0.0.dist-info/METADATA
bosa_cli-0.0.0.dist-info/WHEEL
bosa_cli-0.0.0.dist-info/entry_points.txt
bosa_cli-0.0.0.dist-info/RECORD
