Metadata-Version: 2.3
Name: bosa-cli
Version: 0.0.0
Summary: 
Author: Bosa Engineers
Author-email: bosa-eng@gdplabs.id
Requires-Python: >=3.11, <3.14
Classifier: Programming Language :: Python :: 3
Classifier: Programming Language :: Python :: 3.11
Classifier: Programming Language :: Python :: 3.12
Classifier: Programming Language :: Python :: 3.13
Provides-Extra: dev
Requires-Dist: mypy (>=1.17.0) ; extra == "dev"
Requires-Dist: pre-commit (>=4.2.0) ; extra == "dev"
Requires-Dist: pydantic (>=2.11.7,<3.0.0)
Requires-Dist: pytest (>=8.4.1) ; extra == "dev"
Requires-Dist: pytest-cov (>=6.2.1) ; extra == "dev"
Requires-Dist: requests (>=2.31.0,<3.0.0)
Requires-Dist: ruff (>=0.12.7) ; extra == "dev"
